assmblr/__init__.py
assmblr/strict/__init__.py
assmblr/strict/strict_base.py
assmblr-0.0.3.dist-info/WHEEL
assmblr-0.0.3.dist-info/METADATA
assmblr-0.0.3.dist-info/RECORD
