Metadata-Version: 2.1
Name: assmblr
Version: 0.0.3
Summary: Tools for assembling classes in a concise, performant way
Home-page: https://github.com/AlyceOsbourne/assmblr
Author: Alyce
Author-email: Alyceosbourne@outlook.com
Requires-Python: >=3.10,<4.0
Classifier: Programming Language :: Python :: 3
Classifier: Programming Language :: Python :: 3.10
Classifier: Programming Language :: Python :: 3.11
Project-URL: Repository, https://github.com/AlyceOsbourne/assmblr
